pftcli/__init__.py
pftcli/cli.py
pftcli/config.py
pftcli/context.py
pftcli/core/__init__.py
pftcli/core/callbacks.py
pftcli/core/login.py
pftcli/core/state.py
pftcli/logging.py
pftcli/models/__init__.py
pftcli/models/trade.py
pftcli/plugin_loader.py
pftcli/plugins/__init__.py
pftcli/plugins/tape/__init__.py
pftcli/plugins/tape/command.py
pftcli/plugins/tape/config.py
pftcli/plugins/tape/model.py
pftcli/plugins/tape/view.py
pftcli/profitdll/__init__.py
pftcli/profitdll/profit_dll.py
pftcli/profitdll/profitTypes.py
pftcli/services/__init__.py
pftcli/services/profit_service.py
pftcli-1.0.0.dev0.dist-info/entry_points.txt
pftcli-1.0.0.dev0.dist-info/licenses/LICENSE
pftcli-1.0.0.dev0.dist-info/METADATA
pftcli-1.0.0.dev0.dist-info/WHEEL
pftcli-1.0.0.dev0.dist-info/RECORD
