Metadata-Version: 2.4
Name: pftcli
Version: 1.0.0.dev0
Summary: CLI acessível para automação de trading
License-Expression: GPL-3.0-or-later
License-File: LICENSE
Keywords: trading,cli,automation,market,broker
Author: Valmir França
Author-email: vfranca3@gmail.com
Requires-Python: >=3.13
Classifier: Development Status :: 3 - Alpha
Classifier: Environment :: Console
Classifier: Intended Audience :: Developers
Classifier: Programming Language :: Python :: 3
Classifier: Programming Language :: Python :: 3.13
Classifier: Operating System :: Microsoft :: Windows
Requires-Dist: click (>=8.3.1,<9.0.0)
